{"101": {"agrupador": "Otros Delitos"}, "202": {"agrupador": "Delitos Contra la Libertad e Intimidad de las Personas"}, "203": {"agrupador": "Delitos Contra la Libertad e Intimidad de las Personas"}, "204": {"agrupador": "Delitos Contra la Libertad e Intimidad de las Personas"}, "205": {"agrupador": "Delitos Contra la Libertad e Intimidad de las Personas"}, "221": {"agrupador": "Delitos Contra la Libertad e Intimidad de las Personas"}, "210": {"agrupador": "Delitos Contra la Libertad e Intimidad de las Personas"}, "214": {"agrupador": "Delitos Contra la Libertad e Intimidad de las Personas"}, "216": {"agrupador": "Delitos Funcionarios"}, "218": {"agrupador": "Delitos Funcionarios"}, "12152": {"agrupador": "Delitos Leyes Especiales"}, "223": {"agrupador": "Delitos Funcionarios"}, "224": {"agrupador": "Delitos de tortura, malos tratos, genocidio y lesa humanidad"}, "225": {"agrupador": "Delitos de tortura, malos tratos, genocidio y lesa humanidad"}, "227": {"agrupador": "Delitos de tortura, malos tratos, genocidio y lesa humanidad"}, "228": {"agrupador": "Delitos de tortura, malos tratos, genocidio y lesa humanidad"}, "229": {"agrupador": "Delitos de tortura, malos tratos, genocidio y lesa humanidad"}, "230": {"agrupador": "Delitos de tortura, malos tratos, genocidio y lesa humanidad"}, "231": {"agrupador": "Delitos de tortura, malos tratos, genocidio y lesa humanidad"}, "232": {"agrupador": "Delitos de tortura, malos tratos, genocidio y lesa humanidad"}, "233": {"agrupador": "Delitos de tortura, malos tratos, genocidio y lesa humanidad"}, "234": {"agrupador": "Delitos de tortura, malos tratos, genocidio y lesa humanidad"}, "235": {"agrupador": "Delitos Contra la Libertad e Intimidad de las Personas"}, "236": {"agrupador": "Delitos Contra la Libertad e Intimidad de las Personas"}, "237": {"agrupador": "Delitos Contra la Libertad e Intimidad de las Personas"}, "248": {"agrupador": "Delitos Contra la Libertad e Intimidad de las Personas"}, "249": {"agrupador": "Delitos Contra la Libertad e Intimidad de las Personas"}, "299": {"agrupador": "Delitos Funcionarios"}, "301": {"agrupador": "Delitos Contra la Fe P\u00fablica"}, "12153": {"agrupador": "Delitos Leyes Especiales"}, "856": {"agrupador": "Delitos Econ\u00f3micos y tributarios"}, "304": {"agrupador": "Delitos Contra la Fe P\u00fablica"}, "866": {"agrupador": "Delitos Econ\u00f3micos y tributarios"}, "12031": {"agrupador": "Delitos Contra la Fe P\u00fablica"}, "12051": {"agrupador": "Delitos Econ\u00f3micos y tributarios"}, "309": {"agrupador": "Delitos Contra la Fe P\u00fablica"}, "12055": {"agrupador": "Delitos Leyes Especiales"}, "311": {"agrupador": "Delitos Contra la Fe P\u00fablica"}, "312": {"agrupador": "Delitos Contra la Fe P\u00fablica"}, "399": {"agrupador": "Delitos Contra la Fe P\u00fablica"}, "402": {"agrupador": "Delitos Funcionarios"}, "404": {"agrupador": "Delitos Funcionarios"}, "12056": {"agrupador": "Delitos Econ\u00f3micos y tributarios"}, "406": {"agrupador": "Delitos Funcionarios"}, "408": {"agrupador": "Delitos Funcionarios"}, "409": {"agrupador": "Delitos Funcionarios"}, "410": {"agrupador": "Delitos Funcionarios"}, "411": {"agrupador": "Delitos Funcionarios"}, "413": {"agrupador": "Delitos Funcionarios"}, "415": {"agrupador": "Delitos Funcionarios"}, "416": {"agrupador": "Delitos Funcionarios"}, "417": {"agrupador": "Delitos Funcionarios"}, "418": {"agrupador": "Delitos Funcionarios"}, "419": {"agrupador": "Delitos Funcionarios"}, "420": {"agrupador": "Delitos Funcionarios"}, "421": {"agrupador": "Delitos Funcionarios"}, "422": {"agrupador": "Delitos Funcionarios"}, "423": {"agrupador": "Delitos Funcionarios"}, "424": {"agrupador": "Delitos Funcionarios"}, "425": {"agrupador": "Delitos Econ\u00f3micos y tributarios"}, "426": {"agrupador": "Delitos Econ\u00f3micos y tributarios"}, "429": {"agrupador": "Delitos Funcionarios"}, "499": {"agrupador": "Delitos Funcionarios"}, "501": {"agrupador": "Otros Delitos"}, "502": {"agrupador": "Delitos Contra la Fe P\u00fablica"}, "503": {"agrupador": "Delitos Contra la Fe P\u00fablica"}, "860": {"agrupador": "Delitos Econ\u00f3micos y tributarios"}, "506": {"agrupador": "Delitos Econ\u00f3micos y tributarios"}, "507": {"agrupador": "Delitos Econ\u00f3micos y tributarios"}, "508": {"agrupador": "Otros Delitos"}, "509": {"agrupador": "Otros Delitos"}, "510": {"agrupador": "Otros Delitos"}, "512": {"agrupador": "Otros Delitos"}, "514": {"agrupador": "Otros Delitos"}, "515": {"agrupador": "Delitos Contra la Libertad e Intimidad de las Personas"}, "516": {"agrupador": "Otros Delitos"}, "518": {"agrupador": "Otros Delitos"}, "519": {"agrupador": "Otros Delitos"}, "2003": {"agrupador": "Delitos Leyes Especiales"}, "521": {"agrupador": "Homicidios"}, "522": {"agrupador": "Lesiones"}, "523": {"agrupador": "Delitos Contra la Libertad e Intimidad de las Personas"}, "524": {"agrupador": "Delitos Contra la Libertad e Intimidad de las Personas"}, "525": {"agrupador": "Delitos Contra la Libertad e Intimidad de las Personas"}, "526": {"agrupador": "Otros Delitos"}, "527": {"agrupador": "Otros Delitos"}, "528": {"agrupador": "Delitos Econ\u00f3micos y tributarios"}, "529": {"agrupador": "Delitos Contra la Fe P\u00fablica"}, "530": {"agrupador": "Delitos Contra la Libertad e Intimidad de las Personas"}, "531": {"agrupador": "Lesiones"}, "532": {"agrupador": "Delitos Contra la Libertad e Intimidad de las Personas"}, "533": {"agrupador": "Lesiones"}, "534": {"agrupador": "Otros Delitos"}, "535": {"agrupador": "Otros Delitos"}, "536": {"agrupador": "Otros Delitos"}, "537": {"agrupador": "Delitos Leyes Especiales"}, "538": {"agrupador": "Otros Delitos"}, "539": {"agrupador": "Otros Delitos"}, "540": {"agrupador": "Delitos Leyes Especiales"}, "541": {"agrupador": "Delitos Leyes Especiales"}, "542": {"agrupador": "Otros Delitos"}, "543": {"agrupador": "Delitos Contra la Libertad e Intimidad de las Personas"}, "544": {"agrupador": "Otros Delitos"}, "545": {"agrupador": "Otros Delitos"}, "546": {"agrupador": "Otros Delitos"}, "547": {"agrupador": "Otros Delitos"}, "599": {"agrupador": "Otros Delitos"}, "602": {"agrupador": "Otros Delitos"}, "603": {"agrupador": "Otros Delitos"}, "2004": {"agrupador": "Delitos Leyes Especiales"}, "605": {"agrupador": "Otros Delitos"}, "608": {"agrupador": "Delitos sexuales"}, "609": {"agrupador": "Delitos sexuales"}, "610": {"agrupador": "Delitos sexuales"}, "615": {"agrupador": "Delitos sexuales"}, "617": {"agrupador": "Otros Delitos"}, "619": {"agrupador": "Delitos sexuales"}, "620": {"agrupador": "Delitos sexuales"}, "621": {"agrupador": "Delitos sexuales"}, "623": {"agrupador": "Delitos sexuales"}, "624": {"agrupador": "Otros Delitos"}, "625": {"agrupador": "Otros Delitos"}, "628": {"agrupador": "Delitos sexuales"}, "632": {"agrupador": "Delitos sexuales"}, "633": {"agrupador": "Delitos sexuales"}, "634": {"agrupador": "Delitos sexuales"}, "635": {"agrupador": "Delitos sexuales"}, "636": {"agrupador": "Otros Delitos"}, "637": {"agrupador": "Delitos sexuales"}, "638": {"agrupador": "Delitos sexuales"}, "639": {"agrupador": "Delitos sexuales"}, "640": {"agrupador": "Faltas"}, "647": {"agrupador": "Delitos sexuales"}, "648": {"agrupador": "Delitos sexuales"}, "649": {"agrupador": "Delitos sexuales"}, "650": {"agrupador": "Delitos sexuales"}, "699": {"agrupador": "Delitos sexuales"}, "701": {"agrupador": "Homicidios"}, "702": {"agrupador": "Homicidios"}, "703": {"agrupador": "Homicidios"}, "705": {"agrupador": "Homicidios"}, "706": {"agrupador": "Homicidios"}, "707": {"agrupador": "Homicidios"}, "709": {"agrupador": "Lesiones"}, "710": {"agrupador": "Lesiones"}, "715": {"agrupador": "Otros Delitos"}, "716": {"agrupador": "Otros Delitos"}, "717": {"agrupador": "Lesiones"}, "718": {"agrupador": "Lesiones"}, "720": {"agrupador": "Homicidios"}, "721": {"agrupador": "Delitos Contra la Libertad e Intimidad de las Personas"}, "722": {"agrupador": "Delitos Funcionarios"}, "723": {"agrupador": "Delitos Contra la Libertad e Intimidad de las Personas"}, "724": {"agrupador": "Delitos Contra la Libertad e Intimidad de las Personas"}, "725": {"agrupador": "Delitos Contra la Libertad e Intimidad de las Personas"}, "726": {"agrupador": "Delitos sexuales"}, "727": {"agrupador": "Delitos Contra la Libertad e Intimidad de las Personas"}, "763": {"agrupador": "Otros Delitos"}, "764": {"agrupador": "Otros Delitos"}, "765": {"agrupador": "Otros Delitos"}, "766": {"agrupador": "Homicidios"}, "767": {"agrupador": "Lesiones"}, "768": {"agrupador": "Homicidios"}, "769": {"agrupador": "Homicidios"}, "770": {"agrupador": "Homicidios"}, "799": {"agrupador": "Lesiones"}, "13001": {"agrupador": "Lesiones"}, "802": {"agrupador": "Robos"}, "803": {"agrupador": "Robos"}, "804": {"agrupador": "Robos"}, "806": {"agrupador": "Otros Delitos contra la propiedad"}, "808": {"agrupador": "Robos no violentos"}, "809": {"agrupador": "Robos no violentos"}, "810": {"agrupador": "Robos no violentos"}, "811": {"agrupador": "Otros Delitos contra la propiedad"}, "812": {"agrupador": "Otros Delitos contra la propiedad"}, "814": {"agrupador": "Otros Delitos contra la propiedad"}, "2005": {"agrupador": "Delitos Leyes Especiales"}, "2006": {"agrupador": "Delitos Leyes Especiales"}, "821": {"agrupador": "Hurto"}, "824": {"agrupador": "Delitos Econ\u00f3micos y tributarios"}, "825": {"agrupador": "Otros Delitos contra la propiedad"}, "826": {"agrupador": "Hurto"}, "827": {"agrupador": "Robos"}, "828": {"agrupador": "Robos"}, "829": {"agrupador": "Robos"}, "831": {"agrupador": "Robos no violentos"}, "832": {"agrupador": "Otros Delitos contra la propiedad"}, "833": {"agrupador": "Otros Delitos contra la propiedad"}, "834": {"agrupador": "Otros Delitos contra la propiedad"}, "836": {"agrupador": "Otros Delitos contra la propiedad"}, "838": {"agrupador": "Otros Delitos contra la propiedad"}, "839": {"agrupador": "Otros Delitos contra la propiedad"}, "840": {"agrupador": "Otros Delitos contra la propiedad"}, "841": {"agrupador": "Otros Delitos contra la propiedad"}, "2007": {"agrupador": "Delitos Leyes Especiales"}, "846": {"agrupador": "Hurto"}, "847": {"agrupador": "Hurto"}, "848": {"agrupador": "Hurto"}, "849": {"agrupador": "Otros Delitos contra la propiedad"}, "851": {"agrupador": "Otros Delitos contra la propiedad"}, "2008": {"agrupador": "Delitos Leyes Especiales"}, "853": {"agrupador": "Hurto"}, "854": {"agrupador": "Otros Delitos contra la propiedad"}, "855": {"agrupador": "Otros Delitos contra la propiedad"}, "2009": {"agrupador": "Delitos Leyes Especiales"}, "2010": {"agrupador": "Delitos Leyes Especiales"}, "858": {"agrupador": "Robos no violentos"}, "859": {"agrupador": "Delitos Econ\u00f3micos y tributarios"}, "2011": {"agrupador": "Delitos Leyes Especiales"}, "861": {"agrupador": "Robos"}, "862": {"agrupador": "Robos"}, "863": {"agrupador": "Delitos Econ\u00f3micos y tributarios"}, "864": {"agrupador": "Otros Delitos contra la propiedad"}, "865": {"agrupador": "Delitos Econ\u00f3micos y tributarios"}, "12159": {"agrupador": "Delitos Econ\u00f3micos y tributarios"}, "867": {"agrupador": "Robos"}, "868": {"agrupador": "Robos no violentos"}, "869": {"agrupador": "Otros Delitos contra la propiedad"}, "870": {"agrupador": "Robos no violentos"}, "871": {"agrupador": "Hurto"}, "872": {"agrupador": "Hurto"}, "877": {"agrupador": "Otros Delitos contra la propiedad"}, "891": {"agrupador": "Robos no violentos"}, "892": {"agrupador": "Robos no violentos"}, "896": {"agrupador": "Otros Delitos contra la propiedad"}, "897": {"agrupador": "Delitos Contra la Fe P\u00fablica"}, "898": {"agrupador": "Delitos Econ\u00f3micos y tributarios"}, "899": {"agrupador": "Otros Delitos contra la propiedad"}, "1100": {"agrupador": "Otros Delitos"}, "1101": {"agrupador": "Otros Delitos contra la propiedad"}, "901": {"agrupador": "Cuasidelitos"}, "905": {"agrupador": "Cuasidelitos"}, "910": {"agrupador": "Cuasidelitos"}, "911": {"agrupador": "Cuasidelitos"}, "912": {"agrupador": "Otros Delitos contra la propiedad"}, "999": {"agrupador": "Cuasidelitos"}, "1001": {"agrupador": "Hechos de relevancia criminal"}, "1002": {"agrupador": "Hechos de relevancia criminal"}, "1006": {"agrupador": "Hechos de relevancia criminal"}, "1014": {"agrupador": "Hechos de relevancia criminal"}, "1018": {"agrupador": "Hechos de relevancia criminal"}, "1099": {"agrupador": "Hechos de relevancia criminal"}, "5001": {"agrupador": "Delitos Econ\u00f3micos y tributarios"}, "5002": {"agrupador": "Delitos Econ\u00f3micos y tributarios"}, "5003": {"agrupador": "Delitos Econ\u00f3micos y tributarios"}, "5004": {"agrupador": "Delitos Econ\u00f3micos y tributarios"}, "5005": {"agrupador": "Delitos Econ\u00f3micos y tributarios"}, "857": {"agrupador": "Delitos Econ\u00f3micos y tributarios"}, "207": {"agrupador": "Delitos Contra la Libertad e Intimidad de las Personas"}, "308": {"agrupador": "Delitos Contra la Fe P\u00fablica"}, "310": {"agrupador": "Delitos Contra la Fe P\u00fablica"}, "816": {"agrupador": "Delitos Econ\u00f3micos y tributarios"}, "2002": {"agrupador": "Delitos Leyes Especiales"}, "3002": {"agrupador": "Delitos Econ\u00f3micos y tributarios"}, "3003": {"agrupador": "Delitos Econ\u00f3micos y tributarios"}, "3099": {"agrupador": "Delitos Econ\u00f3micos y tributarios"}, "4003": {"agrupador": "Delitos Econ\u00f3micos y tributarios"}, "4004": {"agrupador": "Delitos Econ\u00f3micos y tributarios"}, "303": {"agrupador": "Delitos Contra la Fe P\u00fablica"}, "4006": {"agrupador": "Delitos Econ\u00f3micos y tributarios"}, "4099": {"agrupador": "Delitos Econ\u00f3micos y tributarios"}, "302": {"agrupador": "Delitos Contra la Fe P\u00fablica"}, "12072": {"agrupador": "Delitos ley de Tr\u00e1nsito"}, "14062": {"agrupador": "Delitos ley de Tr\u00e1nsito"}, "14063": {"agrupador": "Delitos ley de Tr\u00e1nsito"}, "845": {"agrupador": "Delitos Econ\u00f3micos y tributarios"}, "5099": {"agrupador": "Delitos Econ\u00f3micos y tributarios"}, "7001": {"agrupador": "Delitos Ley de Drogas"}, "7006": {"agrupador": "Delitos Ley de Drogas"}, "7007": {"agrupador": "Delitos Ley de Drogas"}, "7014": {"agrupador": "Delitos Ley de Drogas"}, "7031": {"agrupador": "Delitos Ley de Drogas"}, "7032": {"agrupador": "Delitos Ley de Drogas"}, "7033": {"agrupador": "Delitos Ley de Drogas"}, "7034": {"agrupador": "Delitos Ley de Drogas"}, "7037": {"agrupador": "Delitos Ley de Drogas"}, "7042": {"agrupador": "Delitos Ley de Drogas"}, "7043": {"agrupador": "Delitos Ley de Drogas"}, "7044": {"agrupador": "Delitos Ley de Drogas"}, "7045": {"agrupador": "Delitos Ley de Drogas"}, "7046": {"agrupador": "Delitos Ley de Drogas"}, "7047": {"agrupador": "Delitos Ley de Drogas"}, "7048": {"agrupador": "Delitos Ley de Drogas"}, "7049": {"agrupador": "Delitos Ley de Drogas"}, "7050": {"agrupador": "Delitos Ley de Drogas"}, "7051": {"agrupador": "Delitos Ley de Drogas"}, "7052": {"agrupador": "Delitos Ley de Drogas"}, "7053": {"agrupador": "Delitos Ley de Drogas"}, "7054": {"agrupador": "Delitos Ley de Drogas"}, "7099": {"agrupador": "Delitos Ley de Drogas"}, "4005": {"agrupador": "Delitos Econ\u00f3micos y tributarios"}, "505": {"agrupador": "Otros Delitos"}, "9002": {"agrupador": "Delitos contra las leyes de propiedad intelectual e industrial"}, "9003": {"agrupador": "Delitos contra las leyes de propiedad intelectual e industrial"}, "9004": {"agrupador": "Delitos contra las leyes de propiedad intelectual e industrial"}, "9099": {"agrupador": "Delitos contra las leyes de propiedad intelectual e industrial"}, "10001": {"agrupador": "Delitos Leyes Especiales"}, "10008": {"agrupador": "Delitos Leyes Especiales"}, "10009": {"agrupador": "Delitos Leyes Especiales"}, "10010": {"agrupador": "Delitos Leyes Especiales"}, "10011": {"agrupador": "Delitos Leyes Especiales"}, "10012": {"agrupador": "Delitos Leyes Especiales"}, "10013": {"agrupador": "Delitos Leyes Especiales"}, "10014": {"agrupador": "Delitos Leyes Especiales"}, "10015": {"agrupador": "Delitos Leyes Especiales"}, "10016": {"agrupador": "Delitos Leyes Especiales"}, "10017": {"agrupador": "Delitos Leyes Especiales"}, "10018": {"agrupador": "Delitos Leyes Especiales"}, "10037": {"agrupador": "Delitos Leyes Especiales"}, "10038": {"agrupador": "Delitos Leyes Especiales"}, "10039": {"agrupador": "Delitos Leyes Especiales"}, "10040": {"agrupador": "Delitos Leyes Especiales"}, "10041": {"agrupador": "Delitos Leyes Especiales"}, "10042": {"agrupador": "Delitos Leyes Especiales"}, "10099": {"agrupador": "Delitos Leyes Especiales"}, "11001": {"agrupador": "Lesiones"}, "11002": {"agrupador": "Delitos de tortura, malos tratos, genocidio y lesa humanidad"}, "11003": {"agrupador": "Homicidios"}, "11004": {"agrupador": "Delitos Contra la Libertad e Intimidad de las Personas"}, "520": {"agrupador": "Delitos Contra la Fe P\u00fablica"}, "11006": {"agrupador": "Delitos Funcionarios"}, "11099": {"agrupador": "Delitos Leyes Especiales"}, "11101": {"agrupador": "Homicidios"}, "11102": {"agrupador": "Lesiones"}, "11103": {"agrupador": "Delitos Contra la Libertad e Intimidad de las Personas"}, "11104": {"agrupador": "Otros Delitos"}, "12071": {"agrupador": "Delitos ley de Tr\u00e1nsito"}, "12130": {"agrupador": "Delitos Leyes Especiales"}, "12073": {"agrupador": "Delitos ley de Tr\u00e1nsito"}, "12074": {"agrupador": "Delitos ley de Tr\u00e1nsito"}, "12076": {"agrupador": "Delitos ley de Tr\u00e1nsito"}, "12077": {"agrupador": "Delitos ley de Tr\u00e1nsito"}, "12078": {"agrupador": "Delitos ley de Tr\u00e1nsito"}, "12079": {"agrupador": "Delitos ley de Tr\u00e1nsito"}, "12080": {"agrupador": "Delitos ley de Tr\u00e1nsito"}, "12184": {"agrupador": "Delitos ley de Tr\u00e1nsito"}, "12185": {"agrupador": "Delitos ley de Tr\u00e1nsito"}, "14004": {"agrupador": "Delitos ley de Tr\u00e1nsito"}, "14005": {"agrupador": "Delitos ley de Tr\u00e1nsito"}, "14006": {"agrupador": "Delitos ley de Tr\u00e1nsito"}, "14007": {"agrupador": "Delitos ley de Tr\u00e1nsito"}, "14008": {"agrupador": "Delitos ley de Tr\u00e1nsito"}, "14009": {"agrupador": "Delitos ley de Tr\u00e1nsito"}, "14020": {"agrupador": "Delitos ley de Tr\u00e1nsito"}, "14021": {"agrupador": "Delitos ley de Tr\u00e1nsito"}, "14022": {"agrupador": "Delitos ley de Tr\u00e1nsito"}, "14052": {"agrupador": "Delitos ley de Tr\u00e1nsito"}, "14056": {"agrupador": "Delitos ley de Tr\u00e1nsito"}, "14057": {"agrupador": "Delitos ley de Tr\u00e1nsito"}, "14060": {"agrupador": "Delitos ley de Tr\u00e1nsito"}, "306": {"agrupador": "Delitos Contra la Fe P\u00fablica"}, "3001": {"agrupador": "Delitos Leyes Especiales"}, "14064": {"agrupador": "Delitos ley de Tr\u00e1nsito"}, "14065": {"agrupador": "Delitos ley de Tr\u00e1nsito"}, "14066": {"agrupador": "Delitos ley de Tr\u00e1nsito"}, "14087": {"agrupador": "Delitos ley de Tr\u00e1nsito"}, "14088": {"agrupador": "Delitos ley de Tr\u00e1nsito"}, "14089": {"agrupador": "Delitos ley de Tr\u00e1nsito"}, "14090": {"agrupador": "Delitos ley de Tr\u00e1nsito"}, "14091": {"agrupador": "Delitos ley de Tr\u00e1nsito"}, "14092": {"agrupador": "Delitos ley de Tr\u00e1nsito"}, "12010": {"agrupador": "Delitos Leyes Especiales"}, "12021": {"agrupador": "Delitos Leyes Especiales"}, "12022": {"agrupador": "Delitos Leyes Especiales"}, "12023": {"agrupador": "Delitos Leyes Especiales"}, "307": {"agrupador": "Delitos Contra la Fe P\u00fablica"}, "12032": {"agrupador": "Delitos Contra la Fe P\u00fablica"}, "405": {"agrupador": "Delitos Contra la Fe P\u00fablica"}, "12052": {"agrupador": "Delitos Econ\u00f3micos y tributarios"}, "12053": {"agrupador": "Delitos Econ\u00f3micos y tributarios"}, "12054": {"agrupador": "Delitos Econ\u00f3micos y tributarios"}, "8002": {"agrupador": "Delitos contra las leyes de propiedad intelectual e industrial"}, "8003": {"agrupador": "Delitos contra las leyes de propiedad intelectual e industrial"}, "12081": {"agrupador": "Lesiones"}, "12082": {"agrupador": "Delitos Contra la Libertad e Intimidad de las Personas"}, "12086": {"agrupador": "Homicidios"}, "12087": {"agrupador": "Delitos de Justicia Militar"}, "12088": {"agrupador": "Delitos de Justicia Militar"}, "12089": {"agrupador": "Delitos de Justicia Militar"}, "12090": {"agrupador": "Delitos Leyes Especiales"}, "12123": {"agrupador": "Delitos de Justicia Militar"}, "12124": {"agrupador": "Delitos de Justicia Militar"}, "12125": {"agrupador": "Delitos de Justicia Militar"}, "852": {"agrupador": "Delitos Econ\u00f3micos y tributarios"}, "12131": {"agrupador": "Delitos Leyes Especiales"}, "12132": {"agrupador": "Delitos Contra la Libertad e Intimidad de las Personas"}, "12133": {"agrupador": "Delitos Leyes Especiales"}, "12134": {"agrupador": "Delitos Leyes Especiales"}, "12135": {"agrupador": "Delitos Econ\u00f3micos y tributarios"}, "12136": {"agrupador": "Delitos Leyes Especiales"}, "12137": {"agrupador": "Delitos Leyes Especiales"}, "12138": {"agrupador": "Delitos Leyes Especiales"}, "12139": {"agrupador": "Delitos de Justicia Militar"}, "12140": {"agrupador": "Delitos Leyes Especiales"}, "12141": {"agrupador": "Delitos Leyes Especiales"}, "12142": {"agrupador": "Delitos Leyes Especiales"}, "12143": {"agrupador": "Delitos Leyes Especiales"}, "12144": {"agrupador": "Delitos Leyes Especiales"}, "12145": {"agrupador": "Delitos Leyes Especiales"}, "12146": {"agrupador": "Delitos Leyes Especiales"}, "12147": {"agrupador": "Delitos Leyes Especiales"}, "12148": {"agrupador": "Delitos Leyes Especiales"}, "12149": {"agrupador": "Delitos Contra la Fe P\u00fablica"}, "12150": {"agrupador": "Delitos Leyes Especiales"}, "11005": {"agrupador": "Delitos Leyes Especiales"}, "12151": {"agrupador": "Delitos Econ\u00f3micos y tributarios"}, "817": {"agrupador": "Delitos Econ\u00f3micos y tributarios"}, "12155": {"agrupador": "Delitos Leyes Especiales"}, "12156": {"agrupador": "Delitos Leyes Especiales"}, "12157": {"agrupador": "Delitos Leyes Especiales"}, "12158": {"agrupador": "Delitos Econ\u00f3micos y tributarios"}, "604": {"agrupador": "Otros Delitos"}, "12160": {"agrupador": "Delitos Leyes Especiales"}, "12161": {"agrupador": "Delitos Leyes Especiales"}, "12163": {"agrupador": "Delitos Leyes Especiales"}, "12170": {"agrupador": "Delitos Leyes Especiales"}, "12171": {"agrupador": "Delitos Leyes Especiales"}, "12172": {"agrupador": "Delitos Leyes Especiales"}, "12173": {"agrupador": "Delitos Leyes Especiales"}, "12174": {"agrupador": "Delitos Econ\u00f3micos y tributarios"}, "12175": {"agrupador": "Delitos Leyes Especiales"}, "12180": {"agrupador": "Delitos Leyes Especiales"}, "12181": {"agrupador": "Delitos Leyes Especiales"}, "12182": {"agrupador": "Delitos Leyes Especiales"}, "12183": {"agrupador": "Delitos Leyes Especiales"}, "12186": {"agrupador": "Delitos Leyes Especiales"}, "12187": {"agrupador": "Delitos Econ\u00f3micos y tributarios"}, "12188": {"agrupador": "Delitos Leyes Especiales"}, "12189": {"agrupador": "Delitos Leyes Especiales"}, "12190": {"agrupador": "Delitos Econ\u00f3micos y tributarios"}, "12200": {"agrupador": "Delitos Leyes Especiales"}, "12999": {"agrupador": "Delitos Leyes Especiales"}, "13049": {"agrupador": "Delitos Leyes Especiales"}, "13050": {"agrupador": "Delitos Leyes Especiales"}, "13051": {"agrupador": "Delitos Leyes Especiales"}, "15002": {"agrupador": "Otros Delitos"}, "15003": {"agrupador": "Otros Delitos"}, "15007": {"agrupador": "Otros Delitos"}, "16400": {"agrupador": "Delitos Leyes Especiales"}, "16401": {"agrupador": "Delitos Leyes Especiales"}, "16402": {"agrupador": "Delitos Leyes Especiales"}, "16403": {"agrupador": "Delitos Leyes Especiales"}, "22200": {"agrupador": "Delitos de tortura, malos tratos, genocidio y lesa humanidad"}, "22412": {"agrupador": "Delitos Leyes Especiales"}, "22413": {"agrupador": "Delitos Leyes Especiales"}, "22500": {"agrupador": "Delitos Econ\u00f3micos y tributarios"}, "22600": {"agrupador": "Delitos de Justicia Militar"}, "22601": {"agrupador": "Delitos de Justicia Militar"}, "22700": {"agrupador": "Delitos Leyes Especiales"}, "22800": {"agrupador": "Delitos Leyes Especiales"}, "22900": {"agrupador": "Delitos Leyes Especiales"}, "23000": {"agrupador": "Delitos Funcionarios"}, "23100": {"agrupador": "Delitos Leyes Especiales"}, "23200": {"agrupador": "Delitos Leyes Especiales"}, "23300": {"agrupador": "Delitos Leyes Especiales"}, "23400": {"agrupador": "Delitos Leyes Especiales"}, "23500": {"agrupador": "Delitos Leyes Especiales"}, "23600": {"agrupador": "Delitos Leyes Especiales"}, "23601": {"agrupador": "Delitos Leyes Especiales"}, "23602": {"agrupador": "Delitos Leyes Especiales"}, "23700": {"agrupador": "Delitos Econ\u00f3micos y tributarios"}, "23725": {"agrupador": "Delitos Leyes Especiales"}, "23750": {"agrupador": "Delitos Leyes Especiales"}, "23775": {"agrupador": "Delitos Leyes Especiales"}, "23785": {"agrupador": "Homicidios"}, "23786": {"agrupador": "Lesiones"}, "23787": {"agrupador": "Delitos Leyes Especiales"}, "23788": {"agrupador": "Delitos Leyes Especiales"}, "23789": {"agrupador": "Delitos Leyes Especiales"}, "23790": {"agrupador": "Delitos Leyes Especiales"}, "23800": {"agrupador": "Delitos Econ\u00f3micos y tributarios"}, "23801": {"agrupador": "Delitos Leyes Especiales"}, "23802": {"agrupador": "Delitos Leyes Especiales"}, "23803": {"agrupador": "Delitos Leyes Especiales"}, "23804": {"agrupador": "Delitos Leyes Especiales"}, "23900": {"agrupador": "Delitos Leyes Especiales"}, "20001": {"agrupador": "Delitos Leyes Especiales"}, "20002": {"agrupador": "Delitos Leyes Especiales"}, "20003": {"agrupador": "Delitos Leyes Especiales"}, "20004": {"agrupador": "Delitos Leyes Especiales"}, "20005": {"agrupador": "Delitos Leyes Especiales"}, "20006": {"agrupador": "Delitos Leyes Especiales"}, "20007": {"agrupador": "Delitos Leyes Especiales"}, "20099": {"agrupador": "Delitos Leyes Especiales"}, "21001": {"agrupador": "Delitos Leyes Especiales"}, "21002": {"agrupador": "Delitos Leyes Especiales"}, "21003": {"agrupador": "Delitos Leyes Especiales"}, "21099": {"agrupador": "Delitos Leyes Especiales"}, "22100": {"agrupador": "Delitos Leyes Especiales"}, "22101": {"agrupador": "Delitos Leyes Especiales"}, "22400": {"agrupador": "Delitos Leyes Especiales"}, "22401": {"agrupador": "Delitos Leyes Especiales"}, "22410": {"agrupador": "Delitos Econ\u00f3micos y tributarios"}, "22411": {"agrupador": "Delitos Econ\u00f3micos y tributarios"}, "13021": {"agrupador": "Faltas"}, "13022": {"agrupador": "Faltas"}, "13023": {"agrupador": "Faltas"}, "13025": {"agrupador": "Faltas"}, "13026": {"agrupador": "Faltas"}, "13027": {"agrupador": "Faltas"}, "13028": {"agrupador": "Faltas"}, "13030": {"agrupador": "Faltas"}, "13031": {"agrupador": "Faltas"}, "13032": {"agrupador": "Faltas"}, "13033": {"agrupador": "Faltas"}, "13035": {"agrupador": "Faltas"}, "13037": {"agrupador": "Faltas"}, "13038": {"agrupador": "Faltas"}, "13052": {"agrupador": "Faltas"}, "13053": {"agrupador": "Faltas"}, "13096": {"agrupador": "Faltas"}, "13097": {"agrupador": "Faltas"}, "13100": {"agrupador": "Faltas"}, "13101": {"agrupador": "Faltas"}, "13103": {"agrupador": "Faltas"}, "13104": {"agrupador": "Faltas"}, "13105": {"agrupador": "Faltas"}, "13106": {"agrupador": "Faltas"}, "7038": {"agrupador": "Faltas"}, "7039": {"agrupador": "Faltas"}, "18001": {"agrupador": "Faltas"}, "18002": {"agrupador": "Faltas"}, "18003": {"agrupador": "Faltas"}}
